mrexo/Optimizers.py
mrexo/__init__.py
mrexo/aic_nd.py
mrexo/cross_validate_nd.py
mrexo/fit_nd.py
mrexo/mle_utils_nd.py
mrexo/plotting_nd.py
mrexo/predict_nd.py
mrexo/profile_likelihood_nd.py
mrexo/utils_nd.py
mrexo/datasets/MdwarfRuns/MdwarfPrediction.py
mrexo/datasets/MdwarfRuns/Teff_4200_ExcUpperLimits_20231102.csv
mrexo/datasets/MdwarfRuns/MdwarfPlanets_2D_MR_20231102/log_file.txt
mrexo/datasets/MdwarfRuns/MdwarfPlanets_2D_MR_20231102/sample_fit_MdwarfPlanets_2D_MR.py
mrexo/datasets/MdwarfRuns/MdwarfPlanets_2D_MR_20231102/input/DataDict.npy
mrexo/datasets/MdwarfRuns/MdwarfPlanets_2D_MR_20231102/output/Histogram_m.png
mrexo/datasets/MdwarfRuns/MdwarfPlanets_2D_MR_20231102/output/Histogram_r.png
mrexo/datasets/MdwarfRuns/MdwarfPlanets_2D_MR_20231102/output/JointDist.npy
mrexo/datasets/MdwarfRuns/MdwarfPlanets_2D_MR_20231102/output/JointDist.png
mrexo/datasets/MdwarfRuns/MdwarfPlanets_2D_MR_20231102/output/Weights.png
mrexo/datasets/MdwarfRuns/MdwarfPlanets_2D_MR_20231102/output/deg_per_dim.txt
mrexo/datasets/MdwarfRuns/MdwarfPlanets_2D_MR_20231102/output/unpadded_weights.txt
mrexo/datasets/MdwarfRuns/MdwarfPlanets_2D_MR_20231102/output/weights.txt
mrexo/datasets/MdwarfRuns/MdwarfPlanets_2D_MR_20231102/output/other_data_products/DataSequences.txt
mrexo/datasets/MdwarfRuns/MdwarfPlanets_2D_MR_20231102/output/other_data_products/NDimChar.txt
mrexo/datasets/MdwarfRuns/MdwarfPlanets_2D_MR_20231102/output/other_data_products/NDimLabels.txt
mrexo/datasets/MdwarfRuns/MdwarfPlanets_2D_MR_20231102/output/other_data_products/degree_candidates.txt
mrexo/datasets/MdwarfRuns/MdwarfPlanets_2D_MR_20231102/output/other_data_products/likelihood_per_degree.txt
mrexo/datasets/MdwarfRuns/MdwarfPlanets_2D_MR_20231102/output/other_data_products/log_file.txt
mrexo/datasets/MdwarfRuns/MdwarfPlanets_3D_MRStM_20231102/log_file.txt
mrexo/datasets/MdwarfRuns/MdwarfPlanets_3D_MRStM_20231102/sample_fit_MdwarfPlanets_3D_MRStM.py
mrexo-1.1.5.dist-info/LICENSE
mrexo-1.1.5.dist-info/METADATA
mrexo-1.1.5.dist-info/WHEEL
mrexo-1.1.5.dist-info/top_level.txt
mrexo-1.1.5.dist-info/RECORD
