Metadata-Version: 2.1
Name: mrexo
Version: 1.1.5
Summary: A Python code for the non-parametric and probabilistic fitting of planetary and other samples in mass-radius and higher dimensions
Home-page: https://github.com/shbhuk/mrexo
Author: Shubham Kanodia
Author-email: Shubham Kanodia <shbhuk@gmail.com>, "Matthias Y. He" <mhe@nd.edu>
License: GNU GENERAL PUBLIC LICENSE
Project-URL: Homepage, https://mrexo.readthedocs.io
Project-URL: Source, https://github.com/shbhuk/mrexo
Project-URL: Bug Tracker, https://github.com/shbhuk/mrexo/issues
Classifier: Programming Language :: Python :: 3
Classifier: Operating System :: OS Independent
Classifier: Intended Audience :: Science/Research
Requires-Python: >=3.7
License-File: LICENSE
